listener/__init__.py
robotLocalization/__init__.py
xploc/__init__.py
xploc/analyze.py
xploc/api.py
xploc/loader.py
xploc/loader_xml.py
xploc/util.py
xpath_localizer-1.0.4.dist-info/LICENSE
xpath_localizer-1.0.4.dist-info/METADATA
xpath_localizer-1.0.4.dist-info/WHEEL
xpath_localizer-1.0.4.dist-info/entry_points.txt
xpath_localizer-1.0.4.dist-info/top_level.txt
xpath_localizer-1.0.4.dist-info/RECORD
