Metadata-Version: 2.1
Name: xpath-localizer
Version: 1.0.4
Summary: XPATH internationalization and localization helper
Author: Shinichiro Kayano
License: MIT
Keywords: automation cicd internationalization localization playwright robot test xpath
Platform: UNKNOWN
Classifier: License :: OSI Approved :: MIT License
Classifier: Environment :: Console
Classifier: Development Status :: 4 - Beta
Classifier: Programming Language :: Python :: 3.7
Classifier: Programming Language :: Python :: 3.8
Classifier: Programming Language :: Python :: 3.9
Classifier: Programming Language :: Python :: 3.10
Classifier: Framework :: Robot Framework :: Tool
Classifier: Topic :: Software Development :: Internationalization
Classifier: Topic :: Software Development :: Localization
License-File: LICENSE
Requires-Dist: jproperties (>=2.1.1)
Requires-Dist: requests (>=2.31.0)
Provides-Extra: dev
Requires-Dist: pytest ; extra == 'dev'
Requires-Dist: docutils ; extra == 'dev'
Requires-Dist: pygments ; extra == 'dev'
Provides-Extra: optional
Requires-Dist: robotframework ; extra == 'optional'
Requires-Dist: robotframework-seleniumlibrary ; extra == 'optional'
Requires-Dist: robotframework-autorecorder ; extra == 'optional'
Requires-Dist: robotframework-requests ; extra == 'optional'
Requires-Dist: opencv-python ; extra == 'optional'
